escriptorium_collate/__about__.py
escriptorium_collate/__init__.py
escriptorium_collate/collate.py
escriptorium_collate/transcription_layers.py
escriptorium_collate/__assets__/collatex-tools-1.7.1.jar
escriptorium_collate-0.1.15.dist-info/METADATA
escriptorium_collate-0.1.15.dist-info/WHEEL
escriptorium_collate-0.1.15.dist-info/licenses/LICENSE.txt
escriptorium_collate-0.1.15.dist-info/RECORD
