Metadata-Version: 2.4
Name: escriptorium-collate
Version: 0.1.15
Summary: A Python library for collating eScriptorium documents.
Project-URL: Documentation, https://github.com/oeshera/escriptorium-collate#readme
Project-URL: Issues, https://github.com/oeshera/escriptorium-collate/issues
Project-URL: Source, https://github.com/oeshera/escriptorium-collate
Author-email: Osama Eshera <osama.eshera@gmail.com>
License: MIT License
License-File: LICENSE.txt
Classifier: Development Status :: 4 - Beta
Classifier: Programming Language :: Python
Classifier: Programming Language :: Python :: 3.8
Classifier: Programming Language :: Python :: 3.9
Classifier: Programming Language :: Python :: 3.10
Classifier: Programming Language :: Python :: 3.11
Classifier: Programming Language :: Python :: 3.12
Classifier: Programming Language :: Python :: Implementation :: CPython
Classifier: Programming Language :: Python :: Implementation :: PyPy
Requires-Python: >=3.8
Requires-Dist: escriptorium-connector
Requires-Dist: minineedle
Requires-Dist: nltk
Requires-Dist: pydantic
Requires-Dist: python-dotenv
